CHANGES.txt
COPYRIGHT.txt
LICENSE.txt
README.txt
buildout.cfg
setup.py
tl/__init__.py
tl.buildout_mod_python.egg-info/PKG-INFO
tl.buildout_mod_python.egg-info/SOURCES.txt
tl.buildout_mod_python.egg-info/dependency_links.txt
tl.buildout_mod_python.egg-info/entry_points.txt
tl.buildout_mod_python.egg-info/namespace_packages.txt
tl.buildout_mod_python.egg-info/requires.txt
tl.buildout_mod_python.egg-info/top_level.txt
tl.buildout_mod_python.egg-info/zip-safe
tl/buildout_mod_python/__init__.py
tl/buildout_mod_python/module.py