Metadata-Version: 1.0
Name: tl.buildout-mod-python
Version: 0.3
Summary: zc.buildout recipe to build the mod_python Apache module.
Home-page: http://www.thomas-lotze.de/en/software/buildout-recipes/
Author: Thomas Lotze
Author-email: thomas@thomas-lotze.de
License: ZPL 2.1
Keywords: buildout zc.buildout recipe apache modpython mod_python
Platform: UNKNOWN
Classifier: Development Status :: 7 - Inactive
Classifier: Environment :: Console
Classifier: Environment :: Plugins
Classifier: Framework :: Buildout
Classifier: Intended Audience :: Developers
Classifier: Intended Audience :: System Administrators
Classifier: License :: OSI Approved :: Zope Public License
Classifier: Operating System :: Unix
Classifier: Programming Language :: Python
Classifier: Topic :: Software Development :: Build Tools
Classifier: Topic :: System :: Software Distribution
